{
  "status": 202,
  "final_url": "https://www.redfin.com/CA/Los-Angeles/13045-Pacific-Promenade-90094/unit-330/home/21920181",
  "headers": {
    "Server": "CloudFront",
    "Date": "Wed, 01 Oct 2025 12:24:27 GMT",
    "Content-Length": "2040",
    "Connection": "keep-alive",
    "x-amzn-waf-action": "challenge",
    "Cache-Control": "no-store, max-age=0",
    "Content-Type": "text/html; charset=UTF-8",
    "Access-Control-Allow-Origin": "*",
    "Access-Control-Max-Age": "86400",
    "Access-Control-Allow-Methods": "OPTIONS,GET,POST",
    "Access-Control-Expose-Headers": "x-amzn-waf-action",
    "X-Cache": "Error from cloudfront",
    "Via": "1.1 5721fdb09d69998348c3695a2cd176ba.cloudfront.net (CloudFront)",
    "X-Amz-Cf-Pop": "MRS52-P6",
    "X-Amz-Cf-Id": "kwwZDei_-vHRX9zpG7MH1iq7xAAbCWjLjZtP9AdXLd-KT0u3aqT52A=="
  }
}