{
  "status": 200,
  "final_url": "https://www.zillow.com/homedetails/517-Rose-Ave-Venice-CA-90291/456992459_zpid/",
  "headers": {
    "Server": "CloudFront",
    "Content-Type": "text/html; charset=utf-8",
    "Transfer-Encoding": "chunked",
    "Connection": "keep-alive",
    "Date": "Wed, 01 Oct 2025 12:29:32 GMT",
    "via": "1.1 zgs, 1.1 6d3f0112369c770bd0b96a2c6ccd04b4.cloudfront.net (CloudFront)",
    "set-cookie": "zguid=24|%24ab32e834-30b6-4037-89ef-18196ef7c54b; Max-Age=315576000; Expires=Tue, 2 Oct 2035 00:29:32 GMT; Path=/; Domain=.zillow.com, zgsession=1|5a5c3c4b-1989-41cb-9862-ec1e80ca1386; Path=/; Domain=.zillow.com; HTTPOnly",
    "etag": "W/\"52699-Mp1Oak7f9QDXiP8Tqw4E8bSdGDs\"",
    "vary": "Accept-Encoding",
    "content-encoding": "gzip",
    "x-envoy-upstream-service-time": "334",
    "X-Cache": "Miss from cloudfront",
    "X-Amz-Cf-Pop": "MRS53-P3",
    "X-Amz-Cf-Id": "guvpoUGLu2gCBCtrhX_awPRxKimubeRIH6hF7WJ3oF6JdgXYReLIgQ==",
    "X-XSS-Protection": "1",
    "Referrer-Policy": "strict-origin-when-cross-origin",
    "X-Content-Type-Options": "nosniff",
    "Strict-Transport-Security": "max-age=63072000; includeSubDomains; preload",
    "X-DNS-Prefetch-Control": "off"
  }
}