{
  "status": 202,
  "final_url": "https://www.redfin.com/CA/Encino/4939-Petit-Ave-91436/home/4787043",
  "headers": {
    "Server": "CloudFront",
    "Date": "Wed, 01 Oct 2025 12:31:55 GMT",
    "Content-Length": "2040",
    "Connection": "keep-alive",
    "x-amzn-waf-action": "challenge",
    "Cache-Control": "no-store, max-age=0",
    "Content-Type": "text/html; charset=UTF-8",
    "Access-Control-Allow-Origin": "*",
    "Access-Control-Max-Age": "86400",
    "Access-Control-Allow-Methods": "OPTIONS,GET,POST",
    "Access-Control-Expose-Headers": "x-amzn-waf-action",
    "X-Cache": "Error from cloudfront",
    "Via": "1.1 e5c9ccf9978a5dc7af1f4be82495cd98.cloudfront.net (CloudFront)",
    "X-Amz-Cf-Pop": "MRS52-P6",
    "X-Amz-Cf-Id": "wSDpvDMgzPKtGoEtaa5VPwhuuFdwxnAzJQ3xedhRNwgtovMmHm3EYw=="
  }
}