{
  "status": 200,
  "final_url": "https://www.zillow.com/homedetails/4634-N-Racine-Ave-3-Chicago-IL-60640/49917697_zpid/",
  "headers": {
    "Server": "CloudFront",
    "Content-Type": "text/html; charset=utf-8",
    "Transfer-Encoding": "chunked",
    "Connection": "keep-alive",
    "Date": "Wed, 01 Oct 2025 12:59:53 GMT",
    "via": "1.1 zgs, 1.1 31a04db573d633e87bdd7604f64e205a.cloudfront.net (CloudFront)",
    "set-cookie": "zguid=24|%24c6cc6df1-2b09-464d-91ea-ff0c1f199d11; Max-Age=315576000; Expires=Tue, 2 Oct 2035 00:59:53 GMT; Path=/; Domain=.zillow.com, zgsession=1|1ae4df00-7796-418f-9e38-63ac998a48ff; Path=/; Domain=.zillow.com; HTTPOnly",
    "etag": "W/\"4eb16-3avrMm2Sxzv8ryh2Aoa6H2mFLVw\"",
    "vary": "Accept-Encoding",
    "content-encoding": "gzip",
    "x-envoy-upstream-service-time": "224",
    "X-Cache": "Miss from cloudfront",
    "X-Amz-Cf-Pop": "MRS53-P3",
    "X-Amz-Cf-Id": "_bUlCVawN_3iXDT5a8Y_NohMcV-U3u9daPXQHQKEwBVJAndZELla7A==",
    "X-XSS-Protection": "1",
    "Referrer-Policy": "strict-origin-when-cross-origin",
    "X-Content-Type-Options": "nosniff",
    "Strict-Transport-Security": "max-age=63072000; includeSubDomains; preload",
    "X-DNS-Prefetch-Control": "off"
  }
}