{
  "status": 200,
  "final_url": "https://www.zillow.com/homes/30306_rb/",
  "headers": {
    "Server": "CloudFront",
    "Content-Type": "text/html; charset=utf-8",
    "Transfer-Encoding": "chunked",
    "Connection": "keep-alive",
    "Date": "Thu, 09 Oct 2025 14:32:09 GMT",
    "cache-control": "private, no-cache, no-store, max-age=0, must-revalidate",
    "etag": "\"107frq6vyv1kjvl\"",
    "vary": "Accept-Encoding",
    "content-encoding": "gzip",
    "x-envoy-upstream-service-time": "336",
    "via": "1.1 zgs, 1.1 0df028dce5ff77b038214b2a6b5e7eaa.cloudfront.net (CloudFront)",
    "set-cookie": "web-platform-data=%7B%22wp-dd-rum-session%22%3A%7B%22doNotTrack%22%3Atrue%7D%7D; Max-Age=1800; Path=/, zguid=24|%24ffeb901a-5545-4456-8eed-8398536a6e5c; Max-Age=315576000; Expires=Wed, 10 Oct 2035 02:32:09 GMT; Path=/; Domain=.zillow.com, zgsession=1|74182884-e278-40bf-a3ef-d6e9055ae527; Path=/; Domain=.zillow.com; HTTPOnly",
    "X-Cache": "Miss from cloudfront",
    "X-Amz-Cf-Pop": "DEL54-P3",
    "X-Amz-Cf-Id": "p49-kwzCZJXepeXHrgIvuRBNBCeSKQfEWzEAvmgeuZCb4T5NYnshxg==",
    "X-XSS-Protection": "1",
    "Referrer-Policy": "strict-origin-when-cross-origin",
    "X-Content-Type-Options": "nosniff",
    "Strict-Transport-Security": "max-age=63072000; includeSubDomains; preload",
    "X-DNS-Prefetch-Control": "off"
  }
}