[
  {
    "property_id": "497785265595b212255decad8a8a062dad155dc7",
    "street_address": "20 Tarleton Rd",
    "unit_number": "",
    "city": "West Roxbury",
    "state": "MA",
    "postal_code": "02132",
    "latitude": null,
    "longitude": null,
    "interior_area_sqft": 1863,
    "lot_size_sqft": 7146,
    "year_built": 1992,
    "beds": 4.0,
    "baths": 3.0,
    "property_type": "Single Family Residence",
    "property_subtype": "Colonial",
    "condition": "move in ready",
    "features": {},
    "created_at": "2025-09-28T15:55:02.877Z",
    "updated_at": "2025-09-28T15:55:02.877Z"
  },
  {
    "property_id": "550c84d4b85be754d836a83b8ae96e18e1b13fb8",
    "street_address": "107 Stimson St",
    "unit_number": "",
    "city": "West Roxbury",
    "state": "MA",
    "postal_code": "02132",
    "latitude": null,
    "longitude": null,
    "interior_area_sqft": 1700,
    "lot_size_sqft": 13068,
    "year_built": 1942,
    "beds": 3.0,
    "baths": 2.0,
    "property_type": "Single Family Residence",
    "property_subtype": "",
    "condition": "updated",
    "features": {},
    "created_at": "2025-09-28T15:55:35.924Z",
    "updated_at": "2025-09-28T15:55:35.924Z"
  }
]